mumuki/__init__.py
mumuki/base.py
mumuki/i18n.py
mumuki/interactive.py
mumuki/standard.py
mumuki_xce-0.3.dist-info/AUTHORS.rst
mumuki_xce-0.3.dist-info/LICENSE.txt
mumuki_xce-0.3.dist-info/METADATA
mumuki_xce-0.3.dist-info/WHEEL
mumuki_xce-0.3.dist-info/top_level.txt
mumuki_xce-0.3.dist-info/RECORD
