Metadata-Version: 2.1
Name: mumuki-xce
Version: 0.3
Summary: Add a short description here!
Home-page: https://github.com/mumuki/mumuki-xce-py/
Author: Franco Leonardo Bulgarelli
Author-email: franco@mumuki.org
License: MIT
Project-URL: Documentation, https://mumuki.org/
Project-URL: Source, https://github.com/mumuki/mumuki-xce-py/
Project-URL: Tracker, https://github.com/mumuki/mumuki-xce-py/issues
Platform: any
Classifier: Development Status :: 4 - Beta
Classifier: Programming Language :: Python
Requires-Python: >=3.7
License-File: LICENSE.txt
License-File: AUTHORS.rst
Requires-Dist: requests (<3,>=2.27)
Requires-Dist: bs4
Requires-Dist: ipython (<9,>=7.0)
Requires-Dist: beautifulsoup4 (<5,>=4.11)
Requires-Dist: importlib-metadata ; python_version < "3.8"
Provides-Extra: testing
Requires-Dist: setuptools ; extra == 'testing'
Requires-Dist: pytest ; extra == 'testing'
Requires-Dist: pytest-cov ; extra == 'testing'
